flashinfer_bench/__init__.py
flashinfer_bench/env.py
flashinfer_bench/logging.py
flashinfer_bench/utils.py
flashinfer_bench/apply/__init__.py
flashinfer_bench/apply/apply_api.py
flashinfer_bench/apply/config.py
flashinfer_bench/apply/key.py
flashinfer_bench/apply/runtime.py
flashinfer_bench/apply/table.py
flashinfer_bench/bench/__init__.py
flashinfer_bench/bench/benchmark.py
flashinfer_bench/bench/config.py
flashinfer_bench/bench/timing.py
flashinfer_bench/bench/utils.py
flashinfer_bench/bench/evaluators/__init__.py
flashinfer_bench/bench/evaluators/default.py
flashinfer_bench/bench/evaluators/evaluator.py
flashinfer_bench/bench/evaluators/lowbit.py
flashinfer_bench/bench/evaluators/registry.py
flashinfer_bench/bench/evaluators/sampling.py
flashinfer_bench/bench/runner/__init__.py
flashinfer_bench/bench/runner/isolated_runner.py
flashinfer_bench/bench/runner/persistent_runner.py
flashinfer_bench/bench/runner/runner.py
flashinfer_bench/cli/__init__.py
flashinfer_bench/cli/main.py
flashinfer_bench/compile/__init__.py
flashinfer_bench/compile/builder.py
flashinfer_bench/compile/registry.py
flashinfer_bench/compile/runnable.py
flashinfer_bench/compile/builders/__init__.py
flashinfer_bench/compile/builders/cuda_builder.py
flashinfer_bench/compile/builders/python_builder.py
flashinfer_bench/compile/builders/triton_builder.py
flashinfer_bench/data/__init__.py
flashinfer_bench/data/definition.py
flashinfer_bench/data/json_utils.py
flashinfer_bench/data/solution.py
flashinfer_bench/data/trace.py
flashinfer_bench/data/trace_set.py
flashinfer_bench/data/utils.py
flashinfer_bench/integration/__init__.py
flashinfer_bench/integration/patch_manager.py
flashinfer_bench/integration/utils.py
flashinfer_bench/integration/flashinfer/__init__.py
flashinfer_bench/integration/flashinfer/common.py
flashinfer_bench/integration/flashinfer/adapters/__init__.py
flashinfer_bench/integration/flashinfer/adapters/gqa_paged_decode.py
flashinfer_bench-0.1.0.dist-info/licenses/LICENCE
flashinfer_bench-0.1.0.dist-info/licenses/NOTICE
flashinfer_bench-0.1.0.dist-info/METADATA
flashinfer_bench-0.1.0.dist-info/WHEEL
flashinfer_bench-0.1.0.dist-info/entry_points.txt
flashinfer_bench-0.1.0.dist-info/top_level.txt
flashinfer_bench-0.1.0.dist-info/RECORD
