Metadata-Version: 2.4
Name: flashinfer-bench
Version: 0.1.0
Summary: FlashInfer-Bench - AI for AI Infrastructure for Accelerating AI Deployment
Author: FlashInfer team
License: Apache License 2.0
Project-URL: Homepage, https://bench.flashinfer.ai
Project-URL: Documentation, https://bench.flashinfer.ai/docs
Project-URL: Repository, https://github.com/flashinfer-ai/flashinfer-bench
Project-URL: Issues, https://github.com/flashinfer-ai/flashinfer-bench/issues
Keywords: deep-learning,inference,benchmark,flashinfer,gpu
Classifier: Development Status :: 4 - Beta
Classifier: Intended Audience :: Developers
Classifier: Intended Audience :: Science/Research
Classifier: License :: OSI Approved :: Apache Software License
Classifier: Programming Language :: Python :: 3
Classifier: Programming Language :: Python :: 3.9
Classifier: Programming Language :: Python :: 3.10
Classifier: Programming Language :: Python :: 3.11
Classifier: Programming Language :: Python :: 3.12
Classifier: Programming Language :: Python :: 3.13
Classifier: Topic :: Scientific/Engineering :: Artificial Intelligence
Requires-Python: <4.0,>=3.9
License-File: LICENCE
License-File: NOTICE
Requires-Dist: torch==2.8.0
Requires-Dist: pydantic>=2.0.0
Requires-Dist: safetensors>=0.5.0
Requires-Dist: flashinfer-python>=0.3.1
Provides-Extra: dev
Requires-Dist: pytest>=7.0.0; extra == "dev"
Requires-Dist: pytest-cov>=4.0.0; extra == "dev"
Requires-Dist: black>=22.0.0; extra == "dev"
Requires-Dist: isort>=5.0.0; extra == "dev"
Requires-Dist: mypy>=1.0.0; extra == "dev"
Requires-Dist: ruff>=0.1.0; extra == "dev"
Requires-Dist: pre-commit>=3.0.0; extra == "dev"
Requires-Dist: pydoc-markdown>=4.8.2; extra == "dev"
Provides-Extra: cuda12
Requires-Dist: nvidia-cublas-cu12>=12.3; extra == "cuda12"
Requires-Dist: nvidia-cudnn-cu12>=9.0; extra == "cuda12"
Dynamic: license-file
